<?xml version="1.0"?>
<page xmlns:xsi="http://www.w3.org/2001/XMLSchema-instance" layout="admin-2columns-left"
      xsi:noNamespaceSchemaLocation="urn:magento:framework:View/Layout/etc/page_configuration.xsd">
        <body>
            <referenceContainer name="left">
                <block class="Yudiz\Freelancer\Block\Adminhtml\Freelancer\Edit\Tabs" name="freelancer_details_edit_tabs"/>
            </referenceContainer>
            <referenceContainer name="content">
               <block class="Yudiz\Freelancer\Block\Adminhtml\Freelancer\Edit" name="edit_row" cacheable="false"/>
            </referenceContainer>
        </body>
</page>